cx_apikey/__init__.py
cx_apikey/apikey.py
cx_apikey/apikey_exceptions.py
cx_apikey/apikey_factory.py
cx_apikey/apikey_validator.py
cx_apikey-2025.11.3.post2.dist-info/licenses/LICENSE
cx_apikey-2025.11.3.post2.dist-info/METADATA
cx_apikey-2025.11.3.post2.dist-info/WHEEL
cx_apikey-2025.11.3.post2.dist-info/top_level.txt
cx_apikey-2025.11.3.post2.dist-info/RECORD
