Metadata-Version: 2.4
Name: cx-apikey
Version: 2025.11.3.post2
Summary: That is API key generator and manager.
Author-email: Cixo <cixo@cixoelectronic.pl>
Maintainer-email: Cixo <cixo@cixoelectronic.pl>
License-Expression: MIT
Project-URL: Homepage, https://git.cixoelectronic.pl/cixo-electronic/cx-apikey
Project-URL: Repository, https://git.cixoelectronic.pl/cixo-electronic/cx-apikey
Project-URL: Documentation, https://git.cixoelectronic.pl/cixo-electronic/cx-apikey/wiki/Quickstart
Project-URL: Issues, https://git.cixoelectronic.pl/cixo-electronic/cx-apikey/issues
Keywords: API,APIkey,apikey,key,secrets,random,generator
Classifier: Development Status :: 5 - Production/Stable
Classifier: Intended Audience :: Developers
Classifier: Topic :: Software Development :: Libraries
Classifier: Programming Language :: Python :: 3
Requires-Python: >=3.7
License-File: LICENSE
Dynamic: license-file
